flask_required_args/__init__.py
flask_required_args/decorators.py
tests/__init__.py
tests/test_app.py
tests/test_required_args.py
flask_required_args-1.0.0.dist-info/LICENSE
flask_required_args-1.0.0.dist-info/METADATA
flask_required_args-1.0.0.dist-info/WHEEL
flask_required_args-1.0.0.dist-info/top_level.txt
flask_required_args-1.0.0.dist-info/RECORD
