Metadata-Version: 2.1
Name: flask-required-args
Version: 1.0.0
Summary: Upgrade your flask application by defining required arguments
Home-page: https://github.com/fayebutler/flask_required_args
Author: Faye Butler
Author-email: faye.alexandra.butler1@gmail.com
License: UNKNOWN
Platform: UNKNOWN
Classifier: Programming Language :: Python :: 3.7
Classifier: Programming Language :: Python :: 3 :: Only
Classifier: License :: OSI Approved :: Apache Software License
Classifier: Operating System :: OS Independent
Requires-Python: >=3.6
Requires-Dist: flask (==1.0.2)
